machinepy/__init__.py
machinepy-2.0.1.dist-info/LICENSE
machinepy-2.0.1.dist-info/METADATA
machinepy-2.0.1.dist-info/WHEEL
machinepy-2.0.1.dist-info/top_level.txt
machinepy-2.0.1.dist-info/RECORD
