Metadata-Version: 2.1
Name: machinepy
Version: 2.0.1
Summary: Machine learning library
Home-page: UNKNOWN
Author: Dohan Rivas
License: UNKNOWN
Platform: UNKNOWN
Classifier: Programming Language :: Python :: 3
Classifier: License :: OSI Approved :: MIT License
Classifier: Operating System :: OS Independent
Requires-Python: >=3.6
